cheetah/__init__.py
cheetah/_version.py
cheetah/latticejson.py
cheetah/track_methods.py
cheetah/accelerator/__init__.py
cheetah/accelerator/aperture.py
cheetah/accelerator/bpm.py
cheetah/accelerator/cavity.py
cheetah/accelerator/combined_corrector.py
cheetah/accelerator/custom_transfer_map.py
cheetah/accelerator/dipole.py
cheetah/accelerator/drift.py
cheetah/accelerator/element.py
cheetah/accelerator/horizontal_corrector.py
cheetah/accelerator/marker.py
cheetah/accelerator/quadrupole.py
cheetah/accelerator/rbend.py
cheetah/accelerator/screen.py
cheetah/accelerator/segment.py
cheetah/accelerator/sextupole.py
cheetah/accelerator/solenoid.py
cheetah/accelerator/space_charge_kick.py
cheetah/accelerator/transverse_deflecting_cavity.py
cheetah/accelerator/undulator.py
cheetah/accelerator/vertical_corrector.py
cheetah/converters/__init__.py
cheetah/converters/astra.py
cheetah/converters/bmad.py
cheetah/converters/elegant.py
cheetah/converters/nxtables.py
cheetah/converters/ocelot.py
cheetah/converters/utils/__init__.py
cheetah/converters/utils/fortran_namelist.py
cheetah/converters/utils/infix.py
cheetah/converters/utils/rpn.py
cheetah/particles/__init__.py
cheetah/particles/beam.py
cheetah/particles/parameter_beam.py
cheetah/particles/particle_beam.py
cheetah/particles/species.py
cheetah/utils/__init__.py
cheetah/utils/assets.py
cheetah/utils/autograd.py
cheetah/utils/bmadx.py
cheetah/utils/cache.py
cheetah/utils/device.py
cheetah/utils/elementwise_linspace.py
cheetah/utils/kde.py
cheetah/utils/physics.py
cheetah/utils/plot.py
cheetah/utils/statistics.py
cheetah/utils/unique_name_generator.py
cheetah/utils/vector.py
cheetah/utils/warnings.py
cheetah_accelerator-0.8.0.dist-info/licenses/LICENSE
cheetah_accelerator-0.8.0.dist-info/METADATA
cheetah_accelerator-0.8.0.dist-info/WHEEL
cheetah_accelerator-0.8.0.dist-info/top_level.txt
cheetah_accelerator-0.8.0.dist-info/RECORD
