Metadata-Version: 2.4
Name: cheetah-accelerator
Version: 0.8.0
Summary: Fast and differentiable particle accelerator optics simulation for reinforcement learning and optimisation applications.
Home-page: https://github.com/desy-ml/cheetah
Author: Jan Kaiser, Chenran Xu and Christian Hespe
Author-email: jan.kaiser@desy.de
Requires-Python: >=3.11
License-File: LICENSE
Requires-Dist: matplotlib>=3.5
Requires-Dist: numpy>=1.23.3
Requires-Dist: scipy>=1.10.1
Requires-Dist: torch[opt-einsum]>=2.3
Provides-Extra: openpmd
Requires-Dist: openpmd-beamphysics; extra == "openpmd"
Provides-Extra: 3d-visualization
Requires-Dist: trimesh>=4.4.0; extra == "3d-visualization"
Requires-Dist: requests>=2.32.2; extra == "3d-visualization"
Requires-Dist: tqdm>=4.66.0; extra == "3d-visualization"
Dynamic: author
Dynamic: author-email
Dynamic: description
Dynamic: description-content-type
Dynamic: home-page
Dynamic: license-file
Dynamic: provides-extra
Dynamic: requires-dist
Dynamic: requires-python
Dynamic: summary
